MANIFEST.in
README.md
setup.py
cli/__init__.py
cli/reporter.py
django_feed_manager.egg-info/PKG-INFO
django_feed_manager.egg-info/SOURCES.txt
django_feed_manager.egg-info/dependency_links.txt
django_feed_manager.egg-info/entry_points.txt
django_feed_manager.egg-info/requires.txt
django_feed_manager.egg-info/top_level.txt
feedmanager/__init__.py
feedmanager/admin.py
feedmanager/apps.py
feedmanager/models.py
feedmanager/tests.py
feedmanager/urls.py
feedmanager/views.py
feedmanager/migrations/0001_initial.py
feedmanager/migrations/__init__.py