Metadata-Version: 1.1
Name: django-feed-manager
Version: 0.1
Summary: A feed manager for Django, aiming to report automated tasks results in a standard format.
Home-page: https://github.com/Sebatyne/django-feed-manager
Author: Nicolas Wavrant
Author-email: nicolas.wavrant@gmail.com
License: BSD
Keywords: django feed rss
Platform: UNKNOWN
Classifier: Environment :: Web Environment
Classifier: Framework :: Django
Classifier: Development Status :: 4 - Beta
Classifier: Topic :: Utilities
Classifier: License :: OSI Approved :: BSD License
Classifier: Operating System :: OS Independent
Classifier: Programming Language :: Python
Classifier: Programming Language :: Python :: 3
Classifier: Topic :: Internet :: WWW/HTTP
Classifier: Topic :: Internet :: WWW/HTTP :: Dynamic Content
